{
  "items": [
    {
      "id": "p001",
      "title": "小红书AI伙伴数据抓取系统",
      "category": "项目",
      "description": "基于Python+Playwright的自动化抓取与6维度智能评分系统，生成可视化HTML报告",
      "thumbnail": "",
      "detail": "搭建了完整的数据抓取管道：关键词智能轮换、浏览器自动化、6维度评分模型（互动量、内容质量、相关性等），自动筛选高质量帖子并生成可视化HTML报告。支持定时自动执行，包含关键词追踪器、每日报告生成等模块。",
      "highlights": [
        "6维度评分模型自动筛选高质量帖子",
        "搭建每日自动执行管道",
        "关键词智能轮换，防检测机制",
        "生成可视化HTML报告"
      ],
      "techStack": ["Python", "Playwright", "HTML/CSS", "JavaScript"],
      "date": "2026-07",
      "links": { "github": "", "demo": "" },
      "featured": true
    },
    {
      "id": "p002",
      "title": "业财融合与企业财务管控实证研究",
      "category": "文章",
      "description": "基于百万级税调数据和上市公司财务数据，运用DID模型产出三篇学术论文",
      "thumbnail": "",
      "detail": "基于百万级税调数据以及上市公司财务数据，产出三篇学术论文。最新研究运用「vibe coding」方式完成论文数据分析工作，使用Stata进行数据清洗与模型搭建（DID双重差分模型），Python完成大规模数据可视化，分析基尼系数、泰尔指数等不平等指标。论文已于2026年6月25日定稿。",
      "highlights": [
        "百万级税调数据 + 上市公司财务数据",
        "DID双重差分模型因果推断分析",
        "运用「vibe coding」方式完成数据分析",
        "三篇学术论文，已定稿",
        "独立或主持完成各类课程/项目论文超过20篇"
      ],
      "techStack": ["Stata", "Python", "DID模型", "实证分析"],
      "date": "2026-06",
      "links": {},
      "featured": true
    },
    {
      "id": "p003",
      "title": "飞书妙搭AI财务应用",
      "category": "AI应用",
      "description": "通过飞书妙搭设计、生成、调试环境，将代码流程封装为「一键传输」工具",
      "thumbnail": "",
      "detail": "在极兔速运实习期间，利用飞书妙搭设计、生成代码、调试环境，将代码流程封装为「一键传输」工具，降低同事操作门槛。搭建任务工作台，整理二十余份SOP与关联文档，将分散文档转化为可查询的知识管理体系，并用于新人交接。",
      "highlights": [
        "封装「一键传输」工具，降低操作门槛",
        "搭建任务工作台，整理二十余份SOP",
        "分散文档转为可查询知识体系",
        "用于新人交接，提升团队效率"
      ],
      "techStack": ["飞书妙搭", "Codex", "AI工作流"],
      "date": "2026-03",
      "links": {},
      "featured": true
    },
    {
      "id": "p004",
      "title": "Power BI 运单数据自动化看板",
      "category": "项目",
      "description": "针对Excel处理效率低、易出错等问题，运用Python+Power BI搭建业务数据看板",
      "thumbnail": "",
      "detail": "在极兔速运实习期间，针对Excel处理效率低、易出错等问题，运用Python完成数据清洗、数据匹配与格式转换等处理，并通过Power BI搭建业务数据看板，实现单业务处理时长平均缩短70%以上。处理上亿条明细运单数据。",
      "highlights": [
        "处理上亿条明细运单数据",
        "Python数据清洗+格式转换",
        "Power BI搭建业务数据看板",
        "单业务处理时长缩短70%以上"
      ],
      "techStack": ["Power BI", "Python", "Excel"],
      "date": "2026-03",
      "links": {},
      "featured": false
    },
    {
      "id": "p005",
      "title": "行业与竞争对手分析报告",
      "category": "文章",
      "description": "围绕宏观环境和头部速递企业经营状况与市场动态，撰写40余页行业分析报告",
      "thumbnail": "",
      "detail": "在极兔速运实习期间，围绕宏观环境和头部速递企业的经营状况与市场动态，独立撰写40余页行业与竞争对手分析报告，为管理层决策提供数据支持。",
      "highlights": [
        "40余页行业与竞争对手分析报告",
        "覆盖宏观环境与头部速递企业",
        "为管理层决策提供数据支持"
      ],
      "techStack": ["行业研究", "数据分析", "报告撰写"],
      "date": "2026-03",
      "links": {},
      "featured": false
    },
    {
      "id": "p006",
      "title": "安徽省金融投资创新大赛 · 省级三等奖",
      "category": "竞赛",
      "description": "57页上市可行性报告，省级三等奖",
      "thumbnail": "",
      "detail": "作为团队核心成员参与安徽省金融投资创新大赛，完成57页上市可行性报告，涵盖行业分析、财务建模、估值分析等内容，最终获得省级三等奖。",
      "highlights": [
        "57页上市可行性报告",
        "省级三等奖",
        "行业分析+财务建模+估值分析"
      ],
      "techStack": ["财务分析", "行业研究", "报告撰写"],
      "date": "2023",
      "links": {},
      "featured": false
    },
    {
      "id": "p007",
      "title": "国际贸易综合技能大赛 · 省级二等奖",
      "category": "竞赛",
      "description": "Python数据分析与可视化，省级二等奖",
      "thumbnail": "",
      "detail": "运用Python进行贸易数据分析与可视化，完成国际贸易综合技能大赛项目，获得省级二等奖。",
      "highlights": [
        "Python数据分析与可视化",
        "省级二等奖"
      ],
      "techStack": ["Python", "数据分析", "数据可视化"],
      "date": "2022",
      "links": {},
      "featured": false
    },
    {
      "id": "p008",
      "title": "宣州区工业集群调研 · 一等奖",
      "category": "竞赛",
      "description": "43页量化分析报告，一等奖",
      "thumbnail": "",
      "detail": "对宣州区工业集群进行实地调研，完成43页量化分析报告，涵盖产业集群分析、竞争力评估等内容，获得一等奖。",
      "highlights": [
        "43页量化分析报告",
        "一等奖",
        "实地调研+量化分析"
      ],
      "techStack": ["量化分析", "实地调研", "报告撰写"],
      "date": "2022",
      "links": {},
      "featured": false
    },
    {
      "id": "p009",
      "title": "互联网+ / 挑战杯 / 市场调查大赛等",
      "category": "竞赛",
      "description": "互联网+校级银奖、挑战杯校级二等奖、正大杯校级二等奖、三创赛校级三等奖",
      "thumbnail": "",
      "detail": "在校期间积极参与多项学科竞赛，获得互联网+校级银奖、挑战杯校级二等奖、正大杯（市场调查大赛）校级二等奖、三创赛校级三等奖等多项荣誉。",
      "highlights": [
        "互联网+校级银奖",
        "挑战杯校级二等奖",
        "正大杯校级二等奖",
        "三创赛校级三等奖"
      ],
      "techStack": ["团队协作", "项目策划", "数据分析"],
      "date": "2021",
      "links": {},
      "featured": false
    },
    {
      "id": "p010",
      "title": "个人品牌招聘网站",
      "category": "项目",
      "description": "Vue 3 + Vite构建的个人品牌展示站，含简历展示、投递追踪、招聘信息汇总",
      "thumbnail": "",
      "detail": "使用Vue 3 + Vite + Vue Router + ECharts搭建个人品牌网站，包含个人主页（5个Tab：关于我/经历/作品集/成长轨迹/校园&生活）、投递追踪看板（统计+列表+时间线）、招聘信息汇总三大模块。内置管理面板支持表单编辑和JSON导出，部署于GitHub Pages。",
      "highlights": [
        "Vue 3 + Vite + Vue Router + ECharts",
        "5个二级Tab + 管理面板",
        "JSON数据驱动 + localStorage预览",
        "GitHub Pages部署"
      ],
      "techStack": ["Vue 3", "Vite", "ECharts", "CSS变量"],
      "date": "2026-07",
      "links": {},
      "featured": false
    }
  ]
}
